congrid/__init__.py
congrid-0.0.2.dist-info/LICENSE
congrid-0.0.2.dist-info/METADATA
congrid-0.0.2.dist-info/WHEEL
congrid-0.0.2.dist-info/top_level.txt
congrid-0.0.2.dist-info/RECORD
