Metadata-Version: 2.1
Name: congrid
Version: 0.0.2
Summary: A colorful grid built into the console.
Home-page: https://github.com/UCYT5040/congrid.py
Author: Saunders Tech
Author-email: contact@saunderstech.dev
License: UNKNOWN
Project-URL: Bug Tracker, https://github.com/UCYT5040/congrid.py/issues
Platform: UNKNOWN
Classifier: Programming Language :: Python :: 3
Classifier: License :: OSI Approved :: MIT License
Classifier: Operating System :: OS Independent
Requires-Python: >=3.6
